Stoplight.v
//==============================================================================
// Stoplight Module for Lab 4
//
// Note on lights:
// 	Each bit represents the on/off signal for a light.
// 	Bit | Light
// 	------------
// 	0   | Red
// 	1   | Yellow
// 	2   | Green
//==============================================================================

module Stoplight(
	input            clk,         // Clock signal
	input            rst,         // Reset signal for FSM
	input            car_present, // Is there a car on Prospect?
	output reg [2:0] light_pros,  // Prospect Avenue Light
	output reg [2:0] light_wash   // Washington Road Light
);

	// Declare Local Vars Here
	reg [3:0] state;
	reg [3:0] next_state;
	// ...

	// Declare State Names Here
	localparam WASH_GREEN_INIT = 4'd0;
	localparam WASH_WAIT_5 = 4'd1;
	localparam WASH_WAIT_10 = 4'd2;
	localparam WASH_WAIT_15 = 4'd3;
	localparam WASH_YELLOW = 4'd4;
	localparam PROS_GREEN = 4'd5;
	localparam PROS_WAIT_5 = 4'd6;
	localparam PROS_WAIT_10 = 4'd7;
	localparam PROS_WAIT_15 = 4'd8;
	localparam PROS_YELLOW = 4'd9;

	// Light Colors
	localparam RED = 3'b001;
	localparam YLW = 3'b010;
	localparam GRN = 3'b100;

	// Output Combinational Logic
	always @( * ) begin
		// Write your output logic here
		light_pros = 3'b000;
		light_wash = 3'b000;
		if (state == WASH_GREEN_INIT || state == WASH_WAIT_5 || state == WASH_WAIT_10 || state == WASH_WAIT_15) begin
			light_pros = RED;
			light_wash = GRN;
		end
		if (state == WASH_YELLOW) begin
			light_pros = RED;
			light_wash = YLW;
		end
		if (state == PROS_GREEN || state == PROS_WAIT_5 || state == PROS_WAIT_10 || state == PROS_WAIT_15) begin
			light_pros = GRN;
			light_wash = RED;
		end
		if (state == PROS_YELLOW) begin
			light_pros = YLW;
			light_wash = RED;
		end
	end

	// Next State Combinational Logic
	always @( * ) begin
		// Write your Next State Logic Here
		if (state == WASH_GREEN_INIT) next_state = WASH_WAIT_5;
		else if (state == WASH_WAIT_5) next_state = WASH_WAIT_10;
		else if (state == WASH_WAIT_10) next_state = WASH_WAIT_15;
		else if (state == WASH_WAIT_15 && ~car_present) next_state = WASH_WAIT_15;
		else if (state == WASH_WAIT_15 && car_present) next_state = WASH_YELLOW;
		else if (state == WASH_YELLOW) next_state = PROS_GREEN;
		else if (state == PROS_GREEN) next_state = PROS_WAIT_5;
		else if (state == PROS_WAIT_5) next_state = PROS_WAIT_10;
		else if (state == PROS_WAIT_10) next_state = PROS_WAIT_15;
		else if (state == PROS_WAIT_15) next_state = PROS_YELLOW;
		else if (state == PROS_YELLOW) next_state = WASH_GREEN_INIT;
	end

	// State Update Sequential Logic
	always @(posedge clk) begin
		if (rst) begin
			// Update state to reset state
			state <= WASH_GREEN_INIT;
		end
		else begin
			// Update state to next state
			state <= next_state;
		end
	end

endmodule

Stoplight.t.v
//==============================================================================
// Stoplight Testbench Module for Lab 4
//==============================================================================
`timescale 1ns/100ps

`include "Stoplight.v"

`define ASSERT_EQ(ONE, TWO, MSG)               \
	begin                                      \
		if ((ONE) !== (TWO)) begin             \
			$display("\t[FAILURE]:%s", (MSG)); \
			errors = errors + 1;               \
		end                                    \
	end #0

module StoplightTest;

	// Local Vars
	reg clk = 1;
	reg rst = 0;
	reg car = 0;
	reg [4:0] errors = 0;
	wire [2:0] lp, lw;

	// Light Colors
	localparam GRN = 3'b100;
	localparam YLW = 3'b010;
	localparam RED = 3'b001;

	// VCD Dump
	initial begin
		$dumpfile("StoplightTest.vcd");
		$dumpvars;
	end

	// Stoplight Module
	Stoplight light(
		.clk        (clk),
		.rst        (rst),
		.car_present(car),
		.light_pros (lp),
		.light_wash (lw)
	);

	// Clock
	always begin
		#2.5 clk = ~clk;
	end

	// Main Test Logic
	initial begin
		// Reset the controller
		$display("\nResetting the Controller (Washington -> GREEN)...");
		#1; rst = 1; @(posedge clk); // 5 Seconds Elapsed
		#1; rst = 0; @(posedge clk); // 10 Seconds Elapsed

		// Washington should be green
		`ASSERT_EQ(lw, GRN, "Washington light should be green after reset!");
		`ASSERT_EQ(lp, RED, "Prospect light should be red when Washington is green!");

		// Green on Washington
		$display("\nWaiting 25 seconds (Washington -> GREEN)...");
		@(posedge clk); // 15 Seconds Elapsed
		@(posedge clk); // 20 Seconds Elapsed
		@(posedge clk); // 25 Seconds Elapsed
		@(posedge clk); // 30 Seconds Elapsed
		@(posedge clk); // 35 Seconds Elapsed
		@(posedge clk); // 40 Seconds Elapsed

		//Car Arrives on Prospect at 41 secs
		$display("\nCar arrives on Prospect (Washington -> YELLOW)...");
		#1; car = 1; @(posedge clk); #1; //46 Seconds Elapsed

		`ASSERT_EQ(lw, YLW, "Washington light should be turning to yellow.");
		`ASSERT_EQ(lp, RED, "Prospect light should be red when Washington is yellow!");

		$display("\nCar is waiting for the light to turn Green");
		@(posedge clk); #1; car = 0; #1; // Prospect Light Changes from Red to Green, Washington now Red (51 secs)
		
		`ASSERT_EQ(lw, RED, "Washington light is Red when Prosepct is Green!");
		`ASSERT_EQ(lp, GRN, "Prospect light should be green.");

		@(posedge clk); // 55 Seconds Elapsed
		@(posedge clk); // 60 Seconds Elapsed
		@(posedge clk); // 65 Seconds Elapsed 

		$display("\nA stream of cars arrive at Prospect");
		#1; car = 1; #1 // 67 Seconds Elapsed

		// Washington should still be green
		`ASSERT_EQ(lp, GRN, "Prospect light should be green");
		`ASSERT_EQ(lw, RED, "Washington light should be red when Prospect is green!");

		@(posedge clk); // 70 Seconds Elapsed

		$display("\nCars are still at the light");
		#1; // 71 Seconds Elapsed

		`ASSERT_EQ(lp, YLW, "Prospect light should turn yellow");
		`ASSERT_EQ(lw, RED, "Washington light should be red when Prospect is yellow!");

		@(posedge clk); // 75 Seconds Elapsed

		$display("\nCar is trapped on Prospect as the light turns red.");
		#1; // 76 Seconds Elapsed

		`ASSERT_EQ(lw, GRN, "Washington light should turn green");
		`ASSERT_EQ(lp, RED, "Prospect light should be red when Washington is green!");

		@(posedge clk); // 80 Seconds Elapsed
		@(posedge clk); // 85 Seconds Elapsed

		$display("\nThe car on Prospect turns right on red.");
		#1; car = 0; #1; // 87 Seconds Elapsed

		`ASSERT_EQ(lw, GRN, "Washington light is still green");
		`ASSERT_EQ(lp, RED, "Prospect light should be red when Washington is green!");

		@(posedge clk); // 90 Seconds Elapsed
		@(posedge clk); // 95 Seconds Elapsed
		@(posedge clk); // 100 Seconds Elapsed
		@(posedge clk); // 105 Seconds Elapsed

		$display("\nCar arrives on Prospect.");
		#1; car = 1; #1 // 107 Seconds Elapsed

		`ASSERT_EQ(lw, GRN, "Washington light is still green");
		`ASSERT_EQ(lp, RED, "Prospect light should be red when Washington is green!");

		@(posedge clk); // 110 Seconds Elapsed
		@(posedge clk); // 115 Seconds Elapsed

		$display("\nCar on Prospect makes a left turn on Green.");
		#1; car = 0; #1; // 117 Seconds Elapsed

		`ASSERT_EQ(lp, GRN, "Prospect light should have turned green");
		`ASSERT_EQ(lw, RED, "Washington light should be red when Prospect is green!");

		@(posedge clk); // 120 Seconds Elapsed 
		@(posedge clk); // 125 Seconds Elapsed
		@(posedge clk); // 130 Seconds Elapsed

		$display("\nAnother car shows up to the Prospect Light.");
		#1; car = 1; #1; // 132 Seconds Elapsed

		`ASSERT_EQ(lp, GRN, "Prospect light should have turned green");
		`ASSERT_EQ(lw, RED, "Washington light should be red when Prospect is green!");

		@(posedge clk); // 135 Seconds Elapsed

		$display("\nCar on Prospect leaves.");
		#1; car = 0; #1; // 137 Seconds Elapsed

		$display("\nTESTS COMPLETED (%d FAILURES)", errors);
		$finish;
	end

endmodule

StoplightTest.vcd
$date
	Wed Oct 27 18:59:22 2021
$end
$version
	Icarus Verilog
$end
$timescale
	100ps
$end
$scope module StoplightTest $end
$var wire 3 ! lw [2:0] $end
$var wire 3 " lp [2:0] $end
$var reg 1 # car $end
$var reg 1 $ clk $end
$var reg 5 % errors [4:0] $end
$var reg 1 & rst $end
$scope module light $end
$var wire 1 # car_present $end
$var wire 1 $ clk $end
$var wire 1 & rst $end
$var reg 3 ' light_pros [2:0] $end
$var reg 3 ( light_wash [2:0] $end
$var reg 4 ) next_state [3:0] $end
$var reg 4 * state [3:0] $end
$upscope $end
$upscope $end
$enddefinitions $end
#0
$dumpvars
bx *
bx )
bx (
bx '
0&
b0 %
1$
0#
bx "
bx !
$end
#10
1&
#25
0$
#50
b1 )
b100 !
b100 (
b1 "
b1 '
b0 *
1$
#60
0&
#75
0$
#100
b10 )
b100 !
b100 (
b1 "
b1 '
b1 *
1$
#125
0$
#150
b11 )
b100 !
b100 (
b1 "
b1 '
b10 *
1$
#175
0$
#200
b100 !
b100 (
b1 "
b1 '
b11 *
1$
#225
0$
#250
1$
#275
0$
#300
1$
#325
0$
#350
1$
#375
0$
#400
1$
#410
b100 )
1#
#425
0$
#450
b101 )
b10 !
b10 (
b1 "
b1 '
b100 *
1$
#475
0$
#500
b110 )
b1 !
b1 (
b100 "
b100 '
b101 *
1$
#510
0#
#525
0$
#550
b111 )
b1 !
b1 (
b100 "
b100 '
b110 *
1$
#575
0$
#600
b1000 )
b1 !
b1 (
b100 "
b100 '
b111 *
1$
#625
0$
#650
b1001 )
b1 !
b1 (
b100 "
b100 '
b1000 *
1$
#660
1#
#675
0$
#700
b0 )
b1 !
b1 (
b10 "
b10 '
b1001 *
1$
#725
0$
#750
b1 )
b100 !
b100 (
b1 "
b1 '
b0 *
1$
#775
0$
#800
b10 )
b100 !
b100 (
b1 "
b1 '
b1 *
1$
#825
0$
#850
b11 )
b100 !
b100 (
b1 "
b1 '
b10 *
1$
#860
0#
#875
0$
#900
b100 !
b100 (
b1 "
b1 '
b11 *
1$
#925
0$
#950
1$
#975
0$
#1000
1$
#1025
0$
#1050
1$
#1060
b100 )
1#
#1075
0$
#1100
b101 )
b10 !
b10 (
b1 "
b1 '
b100 *
1$
#1125
0$
#1150
b110 )
b1 !
b1 (
b100 "
b100 '
b101 *
1$
#1160
0#
#1175
0$
#1200
b111 )
b1 !
b1 (
b100 "
b100 '
b110 *
1$
#1225
0$
#1250
b1000 )
b1 !
b1 (
b100 "
b100 '
b111 *
1$
#1275
0$
#1300
b1001 )
b1 !
b1 (
b100 "
b100 '
b1000 *
1$
#1310
1#
#1325
0$
#1350
b0 )
b1 !
b1 (
b10 "
b10 '
b1001 *
1$
#1360
0#
